edx_enterprise_data-10.21.16.dist-info/licenses/LICENSE
enterprise_data/__init__.py
enterprise_data/apps.py
enterprise_data/clients.py
enterprise_data/constants.py
enterprise_data/exceptions.py
enterprise_data/filters.py
enterprise_data/models.py
enterprise_data/paginators.py
enterprise_data/renderers.py
enterprise_data/signals.py
enterprise_data/urls.py
enterprise_data/utils.py
enterprise_data/admin_analytics/__init__.py
enterprise_data/admin_analytics/constants.py
enterprise_data/admin_analytics/data_loaders.py
enterprise_data/admin_analytics/database/__init__.py
enterprise_data/admin_analytics/database/utils.py
enterprise_data/admin_analytics/database/filters/__init__.py
enterprise_data/admin_analytics/database/filters/base.py
enterprise_data/admin_analytics/database/filters/fact_completion_admin_dash.py
enterprise_data/admin_analytics/database/filters/fact_engagement_admin_dash.py
enterprise_data/admin_analytics/database/filters/fact_enrollment_admin_dash.py
enterprise_data/admin_analytics/database/filters/mixins.py
enterprise_data/admin_analytics/database/queries/__init__.py
enterprise_data/admin_analytics/database/queries/fact_engagement_admin_dash.py
enterprise_data/admin_analytics/database/queries/fact_enrollment_admin_dash.py
enterprise_data/admin_analytics/database/queries/skills_daily_rollup_admin_dash.py
enterprise_data/admin_analytics/database/query_filters/__init__.py
enterprise_data/admin_analytics/database/query_filters/base.py
enterprise_data/admin_analytics/database/query_filters/between.py
enterprise_data/admin_analytics/database/query_filters/comparison.py
enterprise_data/admin_analytics/database/query_filters/equal.py
enterprise_data/admin_analytics/database/query_filters/in_.py
enterprise_data/admin_analytics/database/query_filters/null.py
enterprise_data/admin_analytics/database/tables/__init__.py
enterprise_data/admin_analytics/database/tables/base.py
enterprise_data/admin_analytics/database/tables/fact_engagement_admin_dash.py
edx_enterprise_data-10.21.16.dist-info/METADATA
edx_enterprise_data-10.21.16.dist-info/WHEEL
edx_enterprise_data-10.21.16.dist-info/top_level.txt
edx_enterprise_data-10.21.16.dist-info/RECORD
