Metadata-Version: 2.4
Name: edx-enterprise-data
Version: 10.21.16
Summary: Enterprise Reporting
Home-page: https://github.com/openedx/edx-enterprise-data
Author: edX
Author-email: oscm@edx.org
License: AGPL 3.0
Classifier: Framework :: Django
Classifier: Framework :: Django :: 4.2
Classifier: Framework :: Django :: 5.2
Classifier: Programming Language :: Python :: 3
Classifier: Programming Language :: Python :: 3.12
License-File: LICENSE
Requires-Dist: Django
Requires-Dist: django-fernet-fields-v2
Requires-Dist: django-filter
Requires-Dist: django-model-utils
Requires-Dist: djangorestframework-csv
Requires-Dist: edx-django-utils
Requires-Dist: edx-drf-extensions
Requires-Dist: edx-opaque-keys
Requires-Dist: edx-rbac
Requires-Dist: edx-rest-api-client
Requires-Dist: factory_boy
Requires-Dist: mysql-connector-python
Requires-Dist: requests
Requires-Dist: rules
Provides-Extra: reporting
Requires-Dist: PGPy; extra == "reporting"
Requires-Dist: awscli; extra == "reporting"
Requires-Dist: boto3; extra == "reporting"
Requires-Dist: celery==5.3.6; extra == "reporting"
Requires-Dist: cryptography; extra == "reporting"
Requires-Dist: https; extra == "reporting"
Requires-Dist: paramiko; extra == "reporting"
Requires-Dist: pyminizip; extra == "reporting"
Requires-Dist: snowflake-connector-python; extra == "reporting"
Requires-Dist: unicodecsv==0.14.1; extra == "reporting"
Requires-Dist: vertica-python; extra == "reporting"
Dynamic: author
Dynamic: author-email
Dynamic: classifier
Dynamic: description
Dynamic: home-page
Dynamic: license
Dynamic: license-file
Dynamic: provides-extra
Dynamic: requires-dist
Dynamic: summary
